Lab_2/Sumador_Restador/Archivos/restSum.v
/*
 * Generated by Digital. Don't modify this file!
 * Any changes will be lost if this file is regenerated.
 */

module Fulladder (
  input A,
  input B,
  input Ci,
  output Co,
  output S
);
  assign S = ((A ^ B) ^ Ci);
  assign Co = ((A & B) | ((A | B) & Ci));
endmodule

module Sumador_4bits (
  input A1,
  input B1,
  input Ci,
  input A2,
  input B2,
  input A3,
  input B3,
  input A4,
  input B4,
  output S1,
  output S2,
  output S3,
  output S4,
  output Co
);
  wire s0;
  wire s5;
  wire s6;
  Fulladder Fulladder_i0 (
    .A( A1 ),
    .B( B1 ),
    .Ci( Ci ),
    .Co( s0 ),
    .S( S1 )
  );
  Fulladder Fulladder_i1 (
    .A( A2 ),
    .B( B2 ),
    .Ci( s0 ),
    .Co( s5 ),
    .S( S2 )
  );
  Fulladder Fulladder_i2 (
    .A( A3 ),
    .B( B3 ),
    .Ci( s5 ),
    .Co( s6 ),
    .S( S3 )
  );
  Fulladder Fulladder_i3 (
    .A( A4 ),
    .B( B4 ),
    .Ci( s6 ),
    .Co( Co ),
    .S( S4 )
  );
endmodule

module MedioRestador (
  input A,
  input B,
  output S,
  output C_out
);
  assign S = (A ^ B);
  assign C_out = (B & ~ A);
endmodule

module RestadorCompleto (
  input A,
  input B,
  input C_in,
  output S,
  output C_out
);
  assign C_out = (((B | C_in) & ~ A) | (C_in & B));
  assign S = (A ^ B ^ C_in);
endmodule

module Restador4bits (
  input A0,
  input B0,
  input A1,
  input B1,
  input A2,
  input B2,
  input A3,
  input B3,
  output S0,
  output S3,
  output C_0ut,
  output S1,
  output S2
);
  wire s4;
  wire s5;
  wire s6;
  MedioRestador MedioRestador_i0 (
    .A( A0 ),
    .B( B0 ),
    .S( S0 ),
    .C_out( s4 )
  );
  RestadorCompleto RestadorCompleto_i1 (
    .A( A1 ),
    .B( B1 ),
    .C_in( s4 ),
    .S( S1 ),
    .C_out( s5 )
  );
  RestadorCompleto RestadorCompleto_i2 (
    .A( A2 ),
    .B( B2 ),
    .C_in( s5 ),
    .S( S2 ),
    .C_out( s6 )
  );
  RestadorCompleto RestadorCompleto_i3 (
    .A( A3 ),
    .B( B3 ),
    .C_in( s6 ),
    .S( S3 ),
    .C_out( C_0ut )
  );
endmodule

module restSum (
  input A1,
  input A2,
  input A3,
  input A4,
  input B1,
  input B2,
  input B3,
  input B4,
  input Ci,
  input Ctrl,
  output S1,
  output S2,
  output S3,
  output C0,
  output S4
);
  wire s0;
  wire s5;
  wire s6;
  wire s7;
  wire s8;
  wire s9;
  wire s10;
  wire s11;
  wire s12;
  wire s13;
  wire s14;
  wire s15;
  wire s16;
  wire s17;
  wire s18;
  wire s19;
  wire s20;
  wire s21;
  wire s22;
  wire s23;
  wire s24;
  wire s25;
  wire s26;
  wire s27;
  wire s28;
  wire s29;
  wire s30;
  assign s6 = (Ci & Ctrl);
  assign s18 = (A1 & ~ Ctrl);
  assign s20 = (A2 & ~ Ctrl);
  assign s22 = (A3 & ~ Ctrl);
  assign s24 = (A4 & ~ Ctrl);
  assign s19 = (B1 & ~ Ctrl);
  assign s21 = (B2 & ~ Ctrl);
  assign s23 = (B3 & ~ Ctrl);
  assign s0 = (A1 & Ctrl);
  assign s7 = (A2 & Ctrl);
  assign s9 = (A3 & Ctrl);
  assign s11 = (A4 & Ctrl);
  assign s5 = (B1 & Ctrl);
  assign s8 = (B2 & Ctrl);
  assign s10 = (B3 & Ctrl);
  assign s12 = (B4 & Ctrl);
  assign s25 = (B4 & ~ Ctrl);
  Sumador_4bits Sumador_4bits_i0 (
    .A1( s0 ),
    .B1( s5 ),
    .Ci( s6 ),
    .A2( s7 ),
    .B2( s8 ),
    .A3( s9 ),
    .B3( s10 ),
    .A4( s11 ),
    .B4( s12 ),
    .S1( s13 ),
    .S2( s14 ),
    .S3( s15 ),
    .S4( s16 ),
    .Co( s17 )
  );
  Restador4bits Restador4bits_i1 (
    .A0( s18 ),
    .B0( s19 ),
    .A1( s20 ),
    .B1( s21 ),
    .A2( s22 ),
    .B2( s23 ),
    .A3( s24 ),
    .B3( s25 ),
    .S0( s26 ),
    .S3( s27 ),
    .C_0ut( s28 ),
    .S1( s29 ),
    .S2( s30 )
  );
  assign S1 = (s13 | s26);
  assign S2 = (s14 | s29);
  assign S3 = (s15 | s30);
  assign S4 = (s16 | s27);
  assign C0 = (s17 | s28);
endmodule

Lab_2/Sumador_Restador/Archivos/restSum_tb.v
module testbech;

  reg [9:0] inputs;
  /* inputs[0] inputs[1] inputs[2] */
   
   /* Me pone todas las interacciones */
  
  integer i; //entera
  initial
  begin
    for (i=0; i<1024; i=i+1)
    begin
      inputs = i;
      #1; //se toma un tic, control de tiempo
    end
  end

  /* // RESULT FOR DEVICE/DESIGN UNDER TEST */
  wire [4:0] outs;
  
  
  // DEVICE/DESIGN UNDER TEST dut
  restSum dut (
      .A4(inputs[9]), .A3(inputs[8]), .A2(inputs[7]), .A1(inputs[6]), .B4(inputs[5]), .B3(inputs[4]), .B2(inputs[3]), .B1(inputs[2]) , .Ci(inputs[1]) , .Ctrl(inputs[0]), 
    .C0(outs[4]), .S4(outs[3]), .S3(outs[2]), .S2(outs[1]), .S1(outs[0])
  );

// input A0,
  // input B0,
  // input A1,
  // input B1,
  // input A2,
  // input B2,
  // input A3,
  // input B3,
  // output S0,
  // output S3,
  // output C_0ut,
  // output S1,
  // output S2
// );


  // WAVES IN VCD TO OPEN IN GTKWAVE
  initial
  begin
    $dumpfile("top.vcd");
    $dumpvars(0, testbech);
  end


endmodule

Lab_2/Sumador_Restador/Archivos/top.vcd
$date
	Fri Oct  6 13:53:50 2023
$end
$version
	Icarus Verilog
$end
$timescale
	1s
$end
$scope module testbech $end
$var wire 5 ! outs [4:0] $end
$var reg 10 " inputs [9:0] $end
$var integer 32 # i [31:0] $end
$scope module dut $end
$var wire 1 $ A1 $end
$var wire 1 % A2 $end
$var wire 1 & A3 $end
$var wire 1 ' A4 $end
$var wire 1 ( B1 $end
$var wire 1 ) B2 $end
$var wire 1 * B3 $end
$var wire 1 + B4 $end
$var wire 1 , C0 $end
$var wire 1 - Ci $end
$var wire 1 . Ctrl $end
$var wire 1 / S1 $end
$var wire 1 0 S2 $end
$var wire 1 1 S3 $end
$var wire 1 2 S4 $end
$var wire 1 3 s0 $end
$var wire 1 4 s10 $end
$var wire 1 5 s11 $end
$var wire 1 6 s12 $end
$var wire 1 7 s18 $end
$var wire 1 8 s19 $end
$var wire 1 9 s20 $end
$var wire 1 : s21 $end
$var wire 1 ; s22 $end
$var wire 1 < s23 $end
$var wire 1 = s24 $end
$var wire 1 > s25 $end
$var wire 1 ? s5 $end
$var wire 1 @ s6 $end
$var wire 1 A s7 $end
$var wire 1 B s8 $end
$var wire 1 C s9 $end
$var wire 1 D s30 $end
$var wire 1 E s29 $end
$var wire 1 F s28 $end
$var wire 1 G s27 $end
$var wire 1 H s26 $end
$var wire 1 I s17 $end
$var wire 1 J s16 $end
$var wire 1 K s15 $end
$var wire 1 L s14 $end
$var wire 1 M s13 $end
$scope module Restador4bits_i1 $end
$var wire 1 7 A0 $end
$var wire 1 9 A1 $end
$var wire 1 ; A2 $end
$var wire 1 = A3 $end
$var wire 1 8 B0 $end
$var wire 1 : B1 $end
$var wire 1 < B2 $end
$var wire 1 > B3 $end
$var wire 1 N s6 $end
$var wire 1 O s5 $end
$var wire 1 P s4 $end
$var wire 1 G S3 $end
$var wire 1 D S2 $end
$var wire 1 E S1 $end
$var wire 1 H S0 $end
$var wire 1 F C_0ut $end
$scope module MedioRestador_i0 $end
$var wire 1 7 A $end
$var wire 1 8 B $end
$var wire 1 P C_out $end
$var wire 1 H S $end
$upscope $end
$scope module RestadorCompleto_i1 $end
$var wire 1 9 A $end
$var wire 1 : B $end
$var wire 1 P C_in $end
$var wire 1 O C_out $end
$var wire 1 E S $end
$upscope $end
$scope module RestadorCompleto_i2 $end
$var wire 1 ; A $end
$var wire 1 < B $end
$var wire 1 O C_in $end
$var wire 1 N C_out $end
$var wire 1 D S $end
$upscope $end
$scope module RestadorCompleto_i3 $end
$var wire 1 = A $end
$var wire 1 > B $end
$var wire 1 N C_in $end
$var wire 1 F C_out $end
$var wire 1 G S $end
$upscope $end
$upscope $end
$scope module Sumador_4bits_i0 $end
$var wire 1 3 A1 $end
$var wire 1 A A2 $end
$var wire 1 C A3 $end
$var wire 1 5 A4 $end
$var wire 1 ? B1 $end
$var wire 1 B B2 $end
$var wire 1 4 B3 $end
$var wire 1 6 B4 $end
$var wire 1 @ Ci $end
$var wire 1 Q s6 $end
$var wire 1 R s5 $end
$var wire 1 S s0 $end
$var wire 1 J S4 $end
$var wire 1 K S3 $end
$var wire 1 L S2 $end
$var wire 1 M S1 $end
$var wire 1 I Co $end
$scope module Fulladder_i0 $end
$var wire 1 3 A $end
$var wire 1 ? B $end
$var wire 1 @ Ci $end
$var wire 1 S Co $end
$var wire 1 M S $end
$upscope $end
$scope module Fulladder_i1 $end
$var wire 1 A A $end
$var wire 1 B B $end
$var wire 1 S Ci $end
$var wire 1 R Co $end
$var wire 1 L S $end
$upscope $end
$scope module Fulladder_i2 $end
$var wire 1 C A $end
$var wire 1 4 B $end
$var wire 1 R Ci $end
$var wire 1 Q Co $end
$var wire 1 K S $end
$upscope $end
$scope module Fulladder_i3 $end
$var wire 1 5 A $end
$var wire 1 6 B $end
$var wire 1 Q Ci $end
$var wire 1 I Co $end
$var wire 1 J S $end
$upscope $end
$upscope $end
$upscope $end
$upscope $end
$enddefinitions $end
$comment Show the parameter values. $end
$dumpall
$end
#0
$dumpvars
0S
0R
0Q
0P
0O
0N
0M
0L
0K
0J
0I
0H
0G
0F
0E
0D
0C
0B
0A
0@
0?
0>
0=
0<
0;
0:
09
08
07
06
05
04
03
02
01
00
0/
0.
0-
0,
0+
0*
0)
0(
0'
0&
0%
0$
b0 #
b0 "
b0 !
$end
#1
1.
b1 "
b1 #
#2
1-
0.
b10 "
b10 #
#3
b1 !
1/
1M
1@
1.
b11 "
b11 #
#4
1,
1F
12
1G
1N
11
1D
1O
b11111 !
10
1E
1H
1P
0M
18
0@
1(
0-
0.
b100 "
b100 #
#5
0,
0F
02
0G
0N
01
0D
0O
b1 !
00
0E
0H
0P
1M
08
1?
1.
b101 "
b101 #
#6
1,
1F
12
1G
1N
11
1D
1O
b11111 !
10
1E
1H
1P
0M
18
0?
1-
0.
b110 "
b110 #
#7
0,
0F
02
0G
0N
01
0D
0O
1L
b10 !
0/
0E
1S
0H
0P
08
1@
1?
1.
b111 "
b111 #
#8
1,
1F
12
1G
1N
b11110 !
11
1D
1O
0L
1E
0S
1:
0@
0?
0(
1)
0-
0.
b1000 "
b1000 #
#9
0,
0F
02
0G
0N
b10 !
01
0D
0O
0E
1L
0:
1B
1.
b1001 "
b1001 #
#10
1,
1F
12
1G
1N
11
1D
1O
1E
b11110 !
10
0L
1:
0B
1-
0.
b1010 "
b1010 #
#11
0,
0F
02
0G
0N
01
0D
0O
0E
b11 !
1/
1L
1M
0:
1@
1B
1.
b1011 "
b1011 #
#12
1,
1F
12
1G
1N
11
1D
1O
b11101 !
00
0L
1H
1P
0M
1:
18
0@
0B
1(
0-
0.
b1100 "
b1100 #
#13
0,
0F
02
0G
0N
01
0D
0O
b11 !
10
0H
0P
1M
1L
08
0:
1?
1B
1.
b1101 "
b1101 #
#14
1,
1F
12
1G
1N
11
1D
1O
b11101 !
00
1H
1P
0M
0L
18
1:
0?
0B
1-
0.
b1110 "
b1110 #
#15
0,
0F
02
0G
0N
0D
1K
0O
1R
0/
b100 !
00
1S
0H
0P
0L
08
0:
1@
1?
1B
1.
b1111 "
b1111 #
#16
1,
1F
12
1G
0K
1N
b11100 !
00
0R
1D
0S
0L
1<
0@
0?
0B
0(
0)
1*
0-
0.
b10000 "
b10000 #
#17
0,
0F
b100 !
02
0G
0N
0D
1K
0<
14
1.
b10001 "
b10001 #
#18
1,
1F
12
1G
1N
1D
b11100 !
11
0K
1<
04
1-
0.
b10010 "
b10010 #
#19
0,
0F
02
0G
0N
0D
b101 !
1/
1K
1M
0<
1@
14
1.
b10011 "
b10011 #
#20
1,
1F
12
1G
1O
1N
10
0D
b11011 !
01
1E
0K
1H
1P
0M
1<
18
0@
04
1(
0-
0.
b10100 "
b10100 #
#21
0,
0F
02
0G
0N
0O
00
0E
0D
b101 !
11
0H
0P
1M
1K
08
0<
1?
14
1.
b10101 "
b10101 #
#22
1,
1F
12
1O
1G
10
1N
1E
0D
b11011 !
01
1H
1P
0M
0K
18
1<
0?
04
1-
0.
b10110 "
b10110 #
#23
0,
0F
02
0G
0N
0O
1L
0/
0E
0D
b110 !
11
1S
0H
0P
1K
08
0<
1@
1?
14
1.
b10111 "
b10111 #
#24
1,
1F
12
1G
1N
1O
0L
0D
b11010 !
01
1E
0S
0K
1<
1:
0@
0?
04
0(
1)
0-
0.
b11000 "
b11000 #
#25
0,
0F
02
0G
0N
0O
0E
0D
b110 !
11
1L
1K
0:
0<
1B
14
1.
b11001 "
b11001 #
#26
1,
1F
12
1G
1O
1N
1E
0D
10
b11010 !
01
0L
0K
1:
1<
0B
04
1-
0.
b11010 "
b11010 #
#27
0,
0F
02
0G
0N
0O
0E
0D
11
b111 !
1/
1L
1K
1M
0:
0<
1@
1B
14
1.
b11011 "
b11011 #
#28
1,
1F
12
1G
1N
1O
0D
00
b11001 !
01
0L
0K
1H
1P
0M
1:
1<
18
0@
0B
04
1(
0-
0.
b11100 "
b11100 #
#29
0,
0F
02
0G
0N
0O
0D
10
b111 !
11
0H
0P
1M
1L
1K
08
0:
0<
1?
1B
14
1.
b11101 "
b11101 #
#30
1,
1F
12
1G
1O
1N
0D
00
b11001 !
01
1H
1P
0M
0L
0K
18
1:
1<
0?
0B
04
1-
0.
b11110 "
b11110 #
#31
0,
0F
0G
0N
1J
1Q
0O
1R
0/
0D
00
b1000 !
01
1S
0H
0P
0L
0K
08
0:
0<
1@
1?
1B
14
1.
b11111 "
b11111 #
#32
1,
0J
1F
00
0R
b11000 !
01
0Q
1G
0S
0L
0K
1>
0@
0?
0B
04
0(
0)
0*
1+
0-
0.
b100000 "
b100000 #
#33
b1000 !
0,
0F
0G
1J
0>
16
1.
b100001 "
b100001 #
#34
b11000 !
1,
1F
1G
0J
1>
06
1-
0.
b100010 "
b100010 #
#35
0,
0F
0G
b1001 !
1/
1J
1M
0>
1@
16
1.
b100011 "
b100011 #
#36
02
1N
11
1D
1,
1O
1F
b10111 !
10
0G
1E
0J
1H
1P
0M
1>
18
0@
06
1(
0-
0.
b100100 "
b100100 #
#37
0,
0F
0N
01
0D
0O
00
0E
b1001 !
12
0G
0H
0P
1M
1J
08
0>
1?
16
1.
b100101 "
b100101 #
#38
02
1N
11
1D
1O
1,
b10111 !
10
1F
1E
0G
1H
1P
0M
0J
18
1>
0?
06
1-
0.
b100110 "
b100110 #
#39
0,
0F
0N
01
0D
0O
1L
0/
0E
b1010 !
12
0G
1S
0H
0P
1J
08
0>
1@
1?
16
1.
b100111 "
b100111 #
#40
02
1N
11
b10110 !
1,
1D
1F
1O
0L
0G
1E
0S
0J
1>
1:
0@
0?
06
0(
1)
0-
0.
b101000 "
b101000 #
#41
0,
0F
0N
01
0D
0O
0E
b1010 !
12
0G
1L
1J
0:
0>
1B
16
1.
b101001 "
b101001 #
#42
02
1N
11
1D
1,
1O
1F
1E
b10110 !
10
0G
0L
0J
1:
1>
0B
06
1-
0.
b101010 "
b101010 #
#43
0,
0F
0N
01
0D
0O
0E
12
0G
b1011 !
1/
1L
1J
1M
0:
0>
1@
1B
16
1.
b101011 "
b101011 #
#44
02
1N
11
1,
1D
1F
1O
b10101 !
00
0G
0L
0J
1H
1P
0M
1:
1>
18
0@
0B
06
1(
0-
0.
b101100 "
b101100 #
#45
0,
0F
0N
01
0D
0O
10
b1011 !
12
0G
0H
0P
1M
1L
1J
08
0:
0>
1?
1B
16
1.
b101101 "
b101101 #
#46
02
1N
11
1D
1,
1O
1F
b10101 !
00
0G
1H
1P
0M
0L
0J
18
1:
1>
0?
0B
06
1-
0.
b101110 "
b101110 #
#47
0,
0F
0N
0D
1K
0O
1R
0/
00
b1100 !
12
0G
1S
0H
0P
0L
1J
08
0:
0>
1@
1?
1B
16
1.
b101111 "
b101111 #
#48
02
1,
0K
1F
1N
b10100 !
00
0R
0G
1D
0S
0L
0J
1>
1<
0@
0?
0B
06
0(
0)
1*
0-
0.
b110000 "
b110000 #
#49
0,
0F
0N
0D
b1100 !
12
0G
1K
1J
0<
0>
14
16
1.
b110001 "
b110001 #
#50
02
1,
1N
1F
1D
b10100 !
11
0G
0K
0J
1<
1>
04
06
1-
0.
b110010 "
b110010 #
#51
0,
0F
0N
0D
12
0G
b1101 !
1/
1K
1J
1M
0<
0>
1@
14
16
1.
b110011 "
b110011 #
#52
02
1,
1O
1N
1F
10
0D
b10011 !
01
0G
1E
0K
0J
1H
1P
0M
1<
1>
18
0@
04
06
1(
0-
0.
b110100 "
b110100 #
#53
0,
0F
0N
0O
00
0E
0D
11
b1101 !
12
0G
0H
0P
1M
1K
1J
08
0<
0>
1?
14
16
1.
b110101 "
b110101 #
#54
02
1O
1,
10
1N
1F
1E
0D
b10011 !
01
0G
1H
1P
0M
0K
0J
18
1<
1>
0?
04
06
1-
0.
b110110 "
b110110 #
#55
0,
0F
0N
0O
1L
0/
0E
0D
11
b1110 !
12
0G
1S
0H
0P
1K
1J
08
0<
0>
1@
1?
14
16
1.
b110111 "
b110111 #
#56
02
1,
1N
1F
1O
0L
0D
b10010 !
01
0G
1E
0S
0K
0J
1<
1>
1:
0@
0?
04
06
0(
1)
0-
0.
b111000 "
b111000 #
#57
0,
0F
0N
0O
0E
0D
11
b1110 !
12
0G
1L
1K
1J
0:
0<
0>
1B
14
16
1.
b111001 "
b111001 #
#58
02
1,
1O
1N
1F
1E
0D
10
b10010 !
01
0G
0L
0K
0J
1:
1<
1>
0B
04
06
1-
0.
b111010 "
b111010 #
#59
0,
0F
0N
0O
0E
0D
11
12
0G
b1111 !
1/
1L
1K
1J
1M
0:
0<
0>
1@
1B
14
16
1.
b111011 "
b111011 #
#60
02
1,
1N
1F
1O
0D
00
b10001 !
01
0G
0L
0K
0J
1H
1P
0M
1:
1<
1>
18
0@
0B
04
06
1(
0-
0.
b111100 "
b111100 #
#61
0,
0F
0N
0O
0D
10
11
b1111 !
12
0G
0H
0P
1M
1L
1K
1J
08
0:
0<
0>
1?
1B
14
16
1.
b111101 "
b111101 #
#62
02
1,
1O
1N
1F
0D
00
b10001 !
01
0G
1H
1P
0M
0L
0K
0J
18
1:
1<
1>
0?
0B
04
06
1-
0.
b111110 "
b111110 #
#63
0F
1I
0N
1Q
0O
1R
0/
0D
00
01
b10000 !
02
0G
1S
0H
0P
0L
0K
0J
08
0:
0<
0>
1@
1?
1B
14
16
1.
b111111 "
b111111 #
#64
0,
00
0R
01
0Q
02
0I
b1 !
1/
0S
0L
0K
0J
1H
17
0@
0?
0B
04
06
1$
0(
0)
0*
0+
0-
0.
b1000000 "
b1000000 #
#65
0H
1M
07
13
1.
b1000001 "
b1000001 #
#66
1H
0M
17
03
1-
0.
b1000010 "
b1000010 #
#67
10
1L
b10 !
0/
1S
0H
07
1@
13
1.
b1000011 "
b1000011 #
#68
0,
0F
02
0G
0N
01
0D
b0 !
00
0O
0L
0E
0S
0P
17
18
0@
03
1(
0-
0.
b1000100 "
b1000100 #
#69
b10 !
10
1L
1S
07
08
13
1?
1.
b1000101 "
b1000101 #
#70
0,
0F
02
0G
0N
01
0D
b0 !
00
0O
0E
0L
0P
0S
17
18
03
0?
1-
0.
b1000110 "
b1000110 #
#71
10
1L
b11 !
1/
1S
1M
07
08
1@
13
1?
1.
b1000111 "
b1000111 #
#72
1,
1F
12
1G
1N
b11111 !
11
1D
1O
0L
1E
1H
0S
0M
17
1:
0@
03
0?
0(
1)
0-
0.
b1001000 "
b1001000 #
#73
0,
0F
02
0G
0N
b11 !
01
0D
0O
0E
0H
1M
1L
07
0:
13
1B
1.
b1001001 "
b1001001 #
#74
1,
1F
12
1G
1N
11
1D
1O
1E
b11111 !
10
1H
0M
0L
17
1:
03
0B
1-
0.
b1001010 "
b1001010 #
#75
0,
0F
02
0G
0N
1K
0D
1R
0O
00
b100 !
0/
0E
1S
0H
0L
07
0:
1@
13
1B
1.
b1001011 "
b1001011 #
#76
1,
1F
12
1G
1N
1E
1D
0K
1O
b11110 !
10
0R
0S
0L
0P
17
1:
18
0@
03
0B
1(
0-
0.
b1001100 "
b1001100 #
#77
0,
0F
02
0G
0N
0D
1K
0O
b100 !
00
1R
0E
1S
0L
07
08
0:
13
1?
1B
1.
b1001101 "
b1001101 #
#78
1,
1F
12
1G
1N
1D
11
1E
1O
0K
b11110 !
10
0R
0P
0S
0L
17
18
1:
03
0?
0B
1-
0.
b1001110 "
b1001110 #
#79
0,
0F
02
0G
0N
0D
1K
0O
00
1R
0E
b101 !
1/
1S
0L
1M
07
08
0:
1@
13
1?
1B
1.
b1001111 "
b1001111 #
#80
1,
1F
12
1G
0K
1N
b11101 !
00
0R
1D
1H
0S
0L
0M
17
1<
0@
03
0?
0B
0(
0)
1*
0-
0.
b1010000 "
b1010000 #
#81
0,
0F
b101 !
02
0G
0N
0D
0H
1M
1K
07
0<
13
14
1.
b1010001 "
b1010001 #
#82
1,
1F
12
1G
1N
1D
b11101 !
11
1H
0M
0K
17
1<
03
04
1-
0.
b1010010 "
b1010010 #
#83
0,
0F
02
0G
10
0N
1L
b110 !
0/
0D
1S
0H
1K
07
0<
1@
13
14
1.
b1010011 "
b1010011 #
#84
1,
1F
12
00
1G
0O
1N
0L
1D
b11100 !
11
0E
0S
0K
0P
17
1<
18
0@
03
04
1(
0-
0.
b1010100 "
b1010100 #
#85
0,
0F
02
0G
0N
b110 !
10
0D
1L
1S
1K
07
08
0<
13
1?
14
1.
b1010101 "
b1010101 #
#86
1,
1F
12
00
0O
1G
1N
0E
1D
0L
b11100 !
11
0P
0S
0K
17
18
1<
03
0?
04
1-
0.
b1010110 "
b1010110 #
#87
0,
0F
02
0G
0N
10
0D
1L
b111 !
1/
1S
1K
1M
07
08
0<
1@
13
1?
14
1.
b1010111 "
b1010111 #
#88
1,
1F
12
1G
1N
1O
0D
0L
b11011 !
01
1E
1H
0S
0K
0M
17
1<
1:
0@
03
0?
04
0(
1)
0-
0.
b1011000 "
b1011000 #
#89
0,
0F
02
0G
0N
0O
0E
0D
b111 !
11
0H
1M
1L
1K
07
0:
0<
13
1B
14
1.
b1011001 "
b1011001 #
#90
1,
1F
12
1G
1O
1N
1E
0D
10
b11011 !
01
1H
0M
0L
0K
17
1:
1<
03
0B
04
1-
0.
b1011010 "
b1011010 #
#91
0,
0F
0G
1J
0N
1Q
1R
0O
00
0/
0E
0D
b1000 !
01
1S
0H
0L
0K
07
0:
0<
1@
13
1B
14
1.
b1011011 "
b1011011 #
#92
1,
1F
1G
12
1E
1N
0J
1O
0D
10
0R
b11010 !
01
0Q
0S
0L
0K
0P
17
1:
1<
18
0@
03
0B
04
1(
0-
0.
b1011100 "
b1011100 #
#93
0,
0F
0G
0N
1J
1Q
0O
00
1R
0E
0D
b1000 !
01
1S
0L
0K
07
08
0:
0<
13
1?
1B
14
1.
b1011101 "
b1011101 #
#94
1,
1F
1G
12
1E
1O
1N
0J
0D
10
0R
b11010 !
01
0Q
0P
0S
0L
0K
17
18
1:
1<
03
0?
0B
04
1-
0.
b1011110 "
b1011110 #
#95
0,
0F
0G
0N
1J
1Q
0O
00
1R
0E
0D
01
b1001 !
1/
1S
0L
0K
1M
07
08
0:
0<
1@
13
1?
1B
14
1.
b1011111 "
b1011111 #
#96
1,
0J
1F
00
0R
b11001 !
01
0Q
1G
1H
0S
0L
0K
0M
17
1>
0@
03
0?
0B
04
0(
0)
0*
1+
0-
0.
b1100000 "
b1100000 #
#97
b1001 !
0,
0F
0G
0H
1M
1J
07
0>
13
16
1.
b1100001 "
b1100001 #
#98
b11001 !
1,
1F
1G
1H
0M
0J
17
1>
03
06
1-
0.
b1100010 "
b1100010 #
#99
0,
10
0F
1L
b1010 !
0/
0G
1S
0H
1J
07
0>
1@
13
16
1.
b1100011 "
b1100011 #
#100
12
0N
01
0D
00
b11000 !
1,
0O
1F
0L
1G
0E
0S
0J
0P
17
1>
18
0@
03
06
1(
0-
0.
b1100100 "
b1100100 #
#101
0,
b1010 !
10
0F
1L
0G
1S
1J
07
08
0>
13
1?
16
1.
b1100101 "
b1100101 #
#102
12
0N
01
0D
00
0O
b11000 !
1,
1F
0E
0L
1G
0P
0S
0J
17
18
1>
03
0?
06
1-
0.
b1100110 "
b1100110 #
#103
0,
10
0F
1L
0G
b1011 !
1/
1S
1J
1M
07
08
0>
1@
13
1?
16
1.
b1100111 "
b1100111 #
#104
02
1N
11
b10111 !
1,
1D
1F
1O
0L
0G
1E
1H
0S
0J
0M
17
1>
1:
0@
03
0?
06
0(
1)
0-
0.
b1101000 "
b1101000 #
#105
0,
0F
0N
01
0D
0O
0E
b1011 !
12
0G
0H
1M
1L
1J
07
0:
0>
13
1B
16
1.
b1101001 "
b1101001 #
#106
02
1N
11
1D
1,
1O
1F
1E
b10111 !
10
0G
1H
0M
0L
0J
17
1:
1>
03
0B
06
1-
0.
b1101010 "
b1101010 #
#107
0,
0F
0N
1K
0D
1R
0O
00
0/
0E
b1100 !
12
0G
1S
0H
0L
1J
07
0:
0>
1@
13
1B
16
1.
b1101011 "
b1101011 #
#108
02
1N
1,
1E
1D
0K
1F
1O
b10110 !
10
0R
0G
0S
0L
0J
0P
17
1:
1>
18
0@
03
0B
06
1(
0-
0.
b1101100 "
b1101100 #
#109
0,
0F
0N
0D
1K
0O
00
1R
0E
b1100 !
12
0G
1S
0L
1J
07
08
0:
0>
13
1?
1B
16
1.
b1101101 "
b1101101 #
#110
02
1N
1D
11
1,
1E
1O
0K
1F
b10110 !
10
0R
0G
0P
0S
0L
0J
17
18
1:
1>
03
0?
0B
06
1-
0.
b1101110 "
b1101110 #
#111
0,
0F
0N
0D
1K
0O
00
1R
0E
12
0G
b1101 !
1/
1S
0L
1J
1M
07
08
0:
0>
1@
13
1?
1B
16
1.
b1101111 "
b1101111 #
#112
02
1,
0K
1F
1N
b10101 !
00
0R
0G
1D
1H
0S
0L
0J
0M
17
1>
1<
0@
03
0?
0B
06
0(
0)
1*
0-
0.
b1110000 "
b1110000 #
#113
0,
0F
0N
0D
b1101 !
12
0G
0H
1M
1K
1J
07
0<
0>
13
14
16
1.
b1110001 "
b1110001 #
#114
02
1,
1N
1F
1D
b10101 !
11
0G
1H
0M
0K
0J
17
1<
1>
03
04
06
1-
0.
b1110010 "
b1110010 #
#115
0,
0F
10
0N
1L
0/
0D
b1110 !
12
0G
1S
0H
1K
1J
07
0<
0>
1@
13
14
16
1.
b1110011 "
b1110011 #
#116
02
00
1,
0O
1N
1F
0L
1D
b10100 !
11
0G
0E
0S
0K
0J
0P
17
1<
1>
18
0@
03
04
06
1(
0-
0.
b1110100 "
b1110100 #
#117
0,
0F
0N
10
0D
1L
b1110 !
12
0G
1S
1K
1J
07
08
0<
0>
13
1?
14
16
1.
b1110101 "
b1110101 #
#118
02
00
0O
1,
1N
1F
0E
1D
0L
b10100 !
11
0G
0P
0S
0K
0J
17
18
1<
1>
03
0?
04
06
1-
0.
b1110110 "
b1110110 #
#119
0,
0F
0N
10
0D
1L
12
0G
b1111 !
1/
1S
1K
1J
1M
07
08
0<
0>
1@
13
1?
14
16
1.
b1110111 "
b1110111 #
#120
02
1,
1N
1F
1O
0D
0L
b10011 !
01
0G
1E
1H
0S
0K
0J
0M
17
1<
1>
1:
0@
03
0?
04
06
0(
1)
0-
0.
b1111000 "
b1111000 #
#121
0,
0F
0N
0O
0E
0D
11
b1111 !
12
0G
0H
1M
1L
1K
1J
07
0:
0<
0>
13
1B
14
16
1.
b1111001 "
b1111001 #
#122
02
1,
1O
1N
1F
1E
0D
10
b10011 !
01
0G
1H
0M
0L
0K
0J
17
1:
1<
1>
03
0B
04
06
1-
0.
b1111010 "
b1111010 #
#123
0F
1I
0N
1Q
1R
0O
00
0/
0E
0D
01
b10000 !
02
0G
1S
0H
0L
0K
0J
07
0:
0<
0>
1@
13
1B
14
16
1.
b1111011 "
b1111011 #
#124
1E
1N
1F
1O
0D
10
0R
01
0Q
b10010 !
02
0I
0G
0S
0L
0K
0J
0P
17
1:
1<
1>
18
0@
03
0B
04
06
1(
0-
0.
b1111100 "
b1111100 #
#125
0F
1I
0N
1Q
0O
00
1R
0E
0D
01
b10000 !
02
0G
1S
0L
0K
0J
07
08
0:
0<
0>
13
1?
1B
14
16
1.
b1111101 "
b1111101 #
#126
1E
1O
1N
1F
0D
10
0R
01
0Q
b10010 !
02
0I
0G
0P
0S
0L
0K
0J
17
18
1:
1<
1>
03
0?
0B
04
06
1-
0.
b1111110 "
b1111110 #
#127
0F
1I
0N
1Q
0O
00
1R
0E
0D
01
02
0G
b10001 !
1/
1S
0L
0K
0J
1M
07
08
0:
0<
0>
1@
13
1?
1B
14
16
1.
b1111111 "
b1111111 #
#128
0,
10
0R
01
0Q
02
0I
1E
b10 !
0/
0S
0L
0K
0J
0M
19
0@
03
0?
0B
04
06
0$
1%
0(
0)
0*
0+
0-
0.
b10000000 "
b10000000 #
#129
0E
1L
09
1A
1.
b10000001 "
b10000001 #
#130
1E
b10 !
10
0L
19
0A
1-
0.
b10000010 "
b10000010 #
#131
0E
b11 !
1/
1L
1M
09
1@
1A
1.
b10000011 "
b10000011 #
#132
b1 !
00
0L
1H
1P
0M
19
18
0@
0A
1(
0-
0.
b10000100 "
b10000100 #
